cy_ai_trainer/__init__.py
cy_ai_trainer/model_trainer.py
cy_ai_trainer/redis_queue.py
cy_ai_trainer-0.0.2.dist-info/LICENSE.txt
cy_ai_trainer-0.0.2.dist-info/METADATA
cy_ai_trainer-0.0.2.dist-info/WHEEL
cy_ai_trainer-0.0.2.dist-info/top_level.txt
cy_ai_trainer-0.0.2.dist-info/RECORD
